{
  "scenes": [
    {
      "entities": [
        {
          "components": [
            {
              "position": {
                "x": 6.642286462010816e-05,
                "y": 0.0,
                "z": -2.0
              },
              "rotation": {
                "x": 0.0003054060216527432,
                "y": 0.0704326182603836,
                "z": -0.0004983032704330981
              },
              "scale": {
                "x": 0.5,
                "y": 0.5,
                "z": 0.5
              },
              "type": "transform"
            },
            {
              "path": "Box",
              "primitive": "box",
              "texturePath": "res/check.png",
              "type": "mesh"
            },
            {
              "box": {
                "x": 0.5,
                "y": 0.5,
                "z": 0.5
              },
              "mass": 1.0,
              "type": "rigidBody"
            }
          ],
          "name": "box"
        },
        {
          "components": [
            {
              "position": {
                "x": -5.0,
                "y": -2.0,
                "z": -11.600000381469727
              },
              "rotation": {
                "x": 0.0,
                "y": -2.4000000953674316,
                "z": 0.0
              },
              "scale": {
                "x": 100.0,
                "y": 1.0,
                "z": 100.0
              },
              "type": "transform"
            },
            {
              "path": "box",
              "primitive": "box",
              "texturePath": "res/texture.jpg",
              "type": "mesh"
            },
            {
              "box": {
                "x": 100.0,
                "y": 1.0,
                "z": 100.0
              },
              "mass": 0.0,
              "type": "rigidBody"
            }
          ],
          "name": "floor"
        },
        {
          "components": [
            {
              "position": {
                "x": 0.0,
                "y": 5.0,
                "z": 0.0
              },
              "rotation": {
                "x": 0.0,
                "y": 0.0,
                "z": 0.0
              },
              "scale": {
                "x": 1.0,
                "y": 1.0,
                "z": 1.0
              },
              "type": "transform"
            },
            {
              "box": {
                "x": 1.0,
                "y": 1.0,
                "z": 1.0
              },
              "mass": 1.0,
              "type": "rigidBody"
            },
            {
              "active": true,
              "position": {
                "x": 0.0,
                "y": 0.0,
                "z": 0.0
              },
              "rotation": {
                "x": 0.0,
                "y": 0.0,
                "z": 0.0
              },
              "type": "camera"
            },
            {
              "type": "PlayerInput"
            },
            {
              "type": "WindowsTest"
            }
          ],
          "name": "Player"
        }
      ],
      "name": "lvl_1"
    },
    {
      "entities": [
        {
          "components": [
            {
              "position": {
                "x": 0.0,
                "y": -2.0,
                "z": 0.0
              },
              "rotation": {
                "x": 0.0,
                "y": 0.0,
                "z": 0.0
              },
              "scale": {
                "x": 100.0,
                "y": 1.0,
                "z": 100.0
              },
              "type": "transform"
            },
            {
              "path": "box",
              "primitive": "box",
              "texturePath": "res/viking_room.png",
              "type": "mesh"
            },
            {
              "box": {
                "x": 100.0,
                "y": 1.0,
                "z": 100.0
              },
              "mass": 0.0,
              "type": "rigidBody"
            }
          ],
          "name": "floorrrrlvl2"
        },
        {
          "components": [
            {
              "position": {
                "x": 0.0,
                "y": 0.0,
                "z": 0.0
              },
              "rotation": {
                "x": 0.0,
                "y": 0.0,
                "z": 0.0
              },
              "scale": {
                "x": 1.0,
                "y": 1.0,
                "z": 1.0
              },
              "type": "transform"
            },
            {
              "path": "res/viking_room.obj",
              "texturePath": "res/viking_room.png",
              "type": "mesh"
            },
            {
              "box": {
                "x": 1.0,
                "y": 1.0,
                "z": 1.0
              },
              "mass": 1.0,
              "type": "rigidBody"
            }
          ],
          "name": "FloorLvl2"
        },
        {
          "components": [
            {
              "position": {
                "x": 0.0,
                "y": 3.0,
                "z": 5.0
              },
              "rotation": {
                "x": -93.7972183227539,
                "y": -60.25933074951172,
                "z": 5.723802089691162
              },
              "scale": {
                "x": 1.0,
                "y": 1.0,
                "z": 1.0
              },
              "type": "transform"
            },
            {
              "box": {
                "x": 1.0,
                "y": 1.0,
                "z": 1.0
              },
              "mass": 1.0,
              "type": "rigidBody"
            },
            {
              "active": true,
              "position": {
                "x": 0.0,
                "y": 0.0,
                "z": 0.0
              },
              "rotation": {
                "x": -3.4055721759796143,
                "y": 177.96070861816406,
                "z": 0.0
              },
              "type": "camera"
            },
            {
              "type": "PlayerInput"
            }
          ],
          "name": "playerLvl2"
        }
      ],
      "name": "lvl_2"
    },
    {
      "entities": [
        {
          "components": [
            {
              "position": {
                "x": 0.0,
                "y": 0.0,
                "z": 0.0
              },
              "rotation": {
                "x": 0.0,
                "y": 0.0,
                "z": 0.0
              },
              "scale": {
                "x": 1.0,
                "y": 1.0,
                "z": 1.0
              },
              "type": "transform"
            },
            {
              "path": "res/viking_room.obj",
              "primitive": "box",
              "texturePath": "res/check.png",
              "type": "mesh"
            }
          ],
          "name": "cubef"
        }
      ],
      "name": "four"
    }
  ]
}